README
setup.py
ppp_cli/__init__.py
ppp_cli/__main__.py
ppp_cli/dot.py
ppp_cli/main.py
ppp_cli/prettyprint.py
ppp_cli.egg-info/PKG-INFO
ppp_cli.egg-info/SOURCES.txt
ppp_cli.egg-info/dependency_links.txt
ppp_cli.egg-info/requires.txt
ppp_cli.egg-info/top_level.txt